<?xml version="1.0" encoding="UTF-8" standalone="no"?>
<configuration version="2.0.0.8">
  <General>
    <HarmonyPath path="../../../.."/>
    <Processor name="PIC32MX795F512L"/>
    <Board name=""/>
    <ForceOptimization flag="true"/>
    <MergeStrategy flag="USER_ALL"/>
  </General>
  <Manifest>
    <Files>
      <File>
        <Name>drv_tmr_mapping.h</Name>
        <Path>Header Files/framework/driver/tmr</Path>
      </File>
      <File>
        <Name>drv_tmr_local.h</Name>
        <Path>Header Files/framework/driver/tmr/src</Path>
      </File>
      <File>
        <Name>drv_usbfs_local.h</Name>
        <Path>Header Files/framework/driver/usb/usbfs/src</Path>
      </File>
      <File>
        <Name>driver_common.h</Name>
        <Path>Header Files/framework/driver</Path>
      </File>
      <File>
        <Name>usb_host_local.h</Name>
        <Path>Header Files/framework/usb/src</Path>
      </File>
      <File>
        <Name>sys_tmr.c</Name>
        <Path>Source Files/framework/system/tmr/src</Path>
      </File>
      <File>
        <Name>drv_usbfs_static.h</Name>
        <Path>Header Files/framework/driver/usb/usbfs</Path>
      </File>
      <File>
        <Name>usb_host_hid_local.h</Name>
        <Path>Header Files/framework/usb/src</Path>
      </File>
      <File>
        <Name>usb_chapter_9.h</Name>
        <Path>Header Files/framework/usb</Path>
      </File>
      <File>
        <Name>usb_host_cdc.c</Name>
        <Path>Source Files/framework/usb/src/dynamic</Path>
      </File>
      <File>
        <Name>driver.h</Name>
        <Path>Header Files/framework/driver</Path>
      </File>
      <File>
        <Name>sys_int_pic32.c</Name>
        <Path>Source Files/framework/system/int/src</Path>
      </File>
      <File>
        <Name>usb_host.c</Name>
        <Path>Source Files/framework/usb/src/dynamic</Path>
      </File>
      <File>
        <Name>sys_clk.h</Name>
        <Path>Header Files/framework/system/clk</Path>
      </File>
      <File>
        <Name>drv_tmr.c</Name>
        <Path>Source Files/framework/driver/tmr/src/dynamic</Path>
      </File>
      <File>
        <Name>sys_int_private.h</Name>
        <Path>Header Files/framework/system/int/src</Path>
      </File>
      <File>
        <Name>drv_tmr_compatibility.h</Name>
        <Path>Header Files/framework/driver/tmr</Path>
      </File>
      <File>
        <Name>sys_tmr_local.h</Name>
        <Path>Header Files/framework/system/tmr/src</Path>
      </File>
      <File>
        <Name>system.h</Name>
        <Path>Header Files/framework/system</Path>
      </File>
      <File>
        <Name>usb_cdc.h</Name>
        <Path>Header Files/framework/usb</Path>
      </File>
      <File>
        <Name>drv_usbfs.h</Name>
        <Path>Header Files/framework/driver/usb/usbfs</Path>
      </File>
      <File>
        <Name>drv_usbfs_host.c</Name>
        <Path>Source Files/framework/driver/usb/usbfs/src/dynamic</Path>
      </File>
      <File>
        <Name>usb_host_cdc_acm.h</Name>
        <Path>Header Files/framework/usb</Path>
      </File>
      <File>
        <Name>sys_int.h</Name>
        <Path>Header Files/framework/system/int</Path>
      </File>
      <File>
        <Name>usb_host_hid_mouse.c</Name>
        <Path>Source Files/framework/usb/src/dynamic</Path>
      </File>
      <File>
        <Name>drv_usb.h</Name>
        <Path>Header Files/framework/driver/usb</Path>
      </File>
      <File>
        <Name>osal_impl_basic.h</Name>
        <Path>Header Files/framework/osal/src</Path>
      </File>
      <File>
        <Name>drv_tmr_variant_mapping.h</Name>
        <Path>Header Files/framework/driver/tmr/src</Path>
      </File>
      <File>
        <Name>drv_usbfs.c</Name>
        <Path>Source Files/framework/driver/usb/usbfs/src/dynamic</Path>
      </File>
      <File>
        <Name>usb_host_hid_mouse_local.h</Name>
        <Path>Header Files/framework/usb/src</Path>
      </File>
      <File>
        <Name>usb_host_hub.c</Name>
        <Path>Source Files/framework/usb/src/dynamic</Path>
      </File>
      <File>
        <Name>drv_tmr.h</Name>
        <Path>Header Files/framework/driver/tmr</Path>
      </File>
      <File>
        <Name>sys_devcon.c</Name>
        <Path>Source Files/framework/system/devcon/src</Path>
      </File>
      <File>
        <Name>sys_tmr.h</Name>
        <Path>Header Files/framework/system/tmr</Path>
      </File>
      <File>
        <Name>usb_host.h</Name>
        <Path>Header Files/framework/usb</Path>
      </File>
      <File>
        <Name>usb_hid.h</Name>
        <Path>Header Files/framework/usb</Path>
      </File>
      <File>
        <Name>osal.h</Name>
        <Path>Header Files/framework/osal</Path>
      </File>
      <File>
        <Name>usb_host_hub_interface.h</Name>
        <Path>Header Files/framework/usb</Path>
      </File>
      <File>
        <Name>usb_common.h</Name>
        <Path>Header Files/framework/usb</Path>
      </File>
      <File>
        <Name>usb_host_hid.c</Name>
        <Path>Source Files/framework/usb/src/dynamic</Path>
      </File>
      <File>
        <Name>sys_ports.h</Name>
        <Path>Header Files/framework/system/ports</Path>
      </File>
      <File>
        <Name>usb_hub.h</Name>
        <Path>Header Files/framework/usb</Path>
      </File>
      <File>
        <Name>sys_common.h</Name>
        <Path>Header Files/framework/system/common</Path>
      </File>
      <File>
        <Name>sys_buffer.h</Name>
        <Path>Header Files/framework/system/common</Path>
      </File>
      <File>
        <Name>usb_host_hub.h</Name>
        <Path>Header Files/framework/usb</Path>
      </File>
      <File>
        <Name>usb_host_cdc_local.h</Name>
        <Path>Header Files/framework/usb/src</Path>
      </File>
      <File>
        <Name>osal_impl_none.h</Name>
        <Path>Header Files/framework/osal/src</Path>
      </File>
      <File>
        <Name>usb_host_hub_mapping.h</Name>
        <Path>Header Files/framework/usb/src</Path>
      </File>
      <File>
        <Name>sys_clk_mapping.h</Name>
        <Path>Header Files/framework/system/clk</Path>
      </File>
      <File>
        <Name>usb_host_hub_local.h</Name>
        <Path>Header Files/framework/usb/src</Path>
      </File>
      <File>
        <Name>osal_definitions.h</Name>
        <Path>Header Files/framework/osal</Path>
      </File>
      <File>
        <Name>sys_int_mapping.h</Name>
        <Path>Header Files/framework/system/int</Path>
      </File>
      <File>
        <Name>usb_host_hid.h</Name>
        <Path>Header Files/framework/usb</Path>
      </File>
      <File>
        <Name>sys_devcon.h</Name>
        <Path>Header Files/framework/system/devcon</Path>
      </File>
      <File>
        <Name>sys_debug.h</Name>
        <Path>Header Files/framework/system/debug</Path>
      </File>
      <File>
        <Name>sys_module.h</Name>
        <Path>Header Files/framework/system/common</Path>
      </File>
      <File>
        <Name>usb_host_hid_mouse.h</Name>
        <Path>Header Files/framework/usb</Path>
      </File>
      <File>
        <Name>sys_devcon_pic32mx.c</Name>
        <Path>Source Files/framework/system/devcon/src</Path>
      </File>
      <File>
        <Name>sys_devcon_local.h</Name>
        <Path>Header Files/framework/system/devcon/src</Path>
      </File>
      <File>
        <Name>usb_host_cdc_acm.c</Name>
        <Path>Source Files/framework/usb/src/dynamic</Path>
      </File>
      <File>
        <Name>drv_usbfs_variant_mapping.h</Name>
        <Path>Header Files/framework/driver/usb/usbfs/src</Path>
      </File>
      <File>
        <Name>sys_queue.h</Name>
        <Path>Header Files/framework/system/common</Path>
      </File>
      <File>
        <Name>drv_usbfs_mapping.h</Name>
        <Path>Header Files/framework/driver/usb/usbfs</Path>
      </File>
      <File>
        <Name>usb_host_client_driver.h</Name>
        <Path>Header Files/framework/usb</Path>
      </File>
      <File>
        <Name>usb_host_cdc.h</Name>
        <Path>Header Files/framework/usb</Path>
      </File>
    </Files>
    <Templates>
      <Template>
        <Name>main.c</Name>
        <Path>Source Files/app</Path>
      </Template>
      <Template>
        <Name>system_config.h</Name>
        <Path>Header Files/app/system_config/pic32mx_usb_sk2_int_dyn</Path>
        <Checksum>81E3EF5C91494EDF6ABA1FCF920673DF</Checksum>
      </Template>
      <Template>
        <Name>bsp.h</Name>
        <Path>Header Files/app/system_config/pic32mx_usb_sk2_int_dyn/bsp</Path>
        <Checksum>CDC15B6204DC381320531899AD84725F</Checksum>
      </Template>
      <Template>
        <Name>system_exceptions.c</Name>
        <Path>Source Files/app/system_config/pic32mx_usb_sk2_int_dyn</Path>
        <Checksum>C111969CA43D6CEA1E9E33A6164E7AE0</Checksum>
      </Template>
      <Template>
        <Name>system_init.c</Name>
        <Path>Source Files/app/system_config/pic32mx_usb_sk2_int_dyn</Path>
        <Checksum>FBF2494A3140D433430BF5ED40C95EB7</Checksum>
      </Template>
      <Template>
        <Name>system_interrupt.c</Name>
        <Path>Source Files/app/system_config/pic32mx_usb_sk2_int_dyn</Path>
        <Checksum>63FB3718B3895018DBD91EBAF461151B</Checksum>
      </Template>
      <Template>
        <Name>sys_clk_static.h</Name>
        <Path>Header Files/app/system_config/pic32mx_usb_sk2_int_dyn/framework/system/clk</Path>
        <Checksum>B4BD59D8D7C4DA95DC5E3B57755FD352</Checksum>
      </Template>
      <Template>
        <Name>app.c</Name>
        <Path>Source Files/app</Path>
      </Template>
      <Template>
        <Name>system_definitions.h</Name>
        <Path>Header Files/app/system_config/pic32mx_usb_sk2_int_dyn</Path>
        <Checksum>BA676648B15F9C24FA31A2B8B30382DB</Checksum>
      </Template>
      <Template>
        <Name>app.h</Name>
        <Path>Header Files/app</Path>
      </Template>
      <Template>
        <Name>sys_clk_static.c</Name>
        <Path>Source Files/app/system_config/pic32mx_usb_sk2_int_dyn/framework/system/clk/src</Path>
        <Checksum>E8C935BED4628875A8C3428DDD07355C</Checksum>
      </Template>
      <Template>
        <Name>bsp.c</Name>
        <Path>Source Files/app/system_config/pic32mx_usb_sk2_int_dyn/bsp</Path>
        <Checksum>A27476DECF3963E23B217F95796161FA</Checksum>
      </Template>
      <Template>
        <Name>sys_ports_static.c</Name>
        <Path>Source Files/app/system_config/pic32mx_usb_sk2_int_dyn/framework/system/ports/src</Path>
        <Checksum>83E28A9509BFB1178054925FE7ED2D75</Checksum>
      </Template>
      <Template>
        <Name>system_tasks.c</Name>
        <Path>Source Files/app/system_config/pic32mx_usb_sk2_int_dyn</Path>
        <Checksum>BB9189172611F9320A16185BB4005D7D</Checksum>
      </Template>
    </Templates>
    <CompilerItems>
      <C32>
        <Include value="D:\git_usb\usb\apps\usb\host\hub_cdc_hid\firmware\src"/>
        <Include value="D:\git_usb\usb\apps\usb\host\hub_cdc_hid\firmware\src\system_config\pic32mx_usb_sk2_int_dyn"/>
        <Include value="D:\git_usb\usb\apps\usb\host\hub_cdc_hid\firmware\src\pic32mx_usb_sk2_int_dyn"/>
        <Include value="D:\git_usb\usb\framework"/>
        <Include value="D:\git_usb\usb\apps\usb\host\hub_cdc_hid\firmware\src\system_config\pic32mx_usb_sk2_int_dyn\framework"/>
        <Include value="../src/system_config/pic32mx_usb_sk2_int_dyn/bsp"/>
      </C32>
    </CompilerItems>
    <Libraries>
      <Library value="../../../../../../bin/framework/peripheral/PIC32MX795F512L_peripherals.a"/>
    </Libraries>
  </Manifest>
</configuration>
